vid2gifx/__init__.py
vid2gifx/cli.py
vid2gifx-0.1.1.dist-info/METADATA
vid2gifx-0.1.1.dist-info/WHEEL
vid2gifx-0.1.1.dist-info/entry_points.txt
vid2gifx-0.1.1.dist-info/top_level.txt
vid2gifx-0.1.1.dist-info/RECORD
