Metadata-Version: 2.4
Name: vid2gifx
Version: 0.1.1
Summary: FFmpeg-only video to GIF converter with palettegen/paletteuse and size targeting.
Author-email: thecoderider <thecoderider42@gmail.com>
License: MIT
Project-URL: Homepage, https://github.com/the-code-rider/vid2gif
Project-URL: Issues, https://github.com/the-code-rider/video2gif/issues
Keywords: ffmpeg,gif,video,conversion,palettegen,paletteuse
Classifier: Programming Language :: Python :: 3
Classifier: Programming Language :: Python :: 3 :: Only
Classifier: License :: OSI Approved :: MIT License
Classifier: Environment :: Console
Classifier: Topic :: Multimedia :: Video
Classifier: Topic :: Multimedia :: Graphics
Classifier: Operating System :: OS Independent
Requires-Python: >=3.8
